Workbook

Sheet Fuentes
A1: SINTÉTICO — NO ES UNA INVERSIÓN
A2: source_id | B2: url | C2: title | D2: published_on | E2: retrieved_on | F2: sha256 | G2: locator
A3: synthetic-annual | B3: synthetic://ares/annual/2024 | C3: Synthetic annual fixture | D3: 2025-02-01 | E3: 2025-03-01 | F3: 039a89b8667235cad37c28559d72a824fb4a9e901aafa2d62e6fb054a282f89e | G3: page 1
A4: synthetic-history | B4: synthetic://ares/history | C4: Synthetic historical fixture | D4: 2025-02-01 | E4: 2025-03-01 | F4: e33af9f583fd4a8894b4ace43b6153cbae733b4d269ecc589ceed2c8479e19ad | G4: rows

Sheet Historicos
A1: SINTÉTICO — NO ES UNA INVERSIÓN
A2: year | B2: revenue | C2: ebit | D2: net_income | E2: cfo | F2: capex | G2: assets | H2: liabilities | I2: equity | J2: source_id
A3: 2020 | B3: 800 | C3: 144 | D3: 80 | E3: 100 | F3: 40 | G3: 1300 | H3: 520 | I3: 780 | J3: synthetic-history
A4: 2021 | B4: 850 | C4: 153 | D4: 85 | E4: 105 | F4: 42.5 | G4: 1350 | H4: 540 | I4: 810 | J4: synthetic-history
A5: 2022 | B5: 900 | C5: 162 | D5: 90 | E5: 110 | F5: 45 | G5: 1400 | H5: 560 | I5: 840 | J5: synthetic-history
A6: 2023 | B6: 950 | C6: 171 | D6: 95 | E6: 115 | F6: 47.5 | G6: 1450 | H6: 580 | I6: 870 | J6: synthetic-history
A7: 2024 | B7: 1000 | C7: 180 | D7: 100 | E7: 120 | F7: 50 | G7: 1500 | H7: 600 | I7: 900 | J7: synthetic-history

Sheet Ajustes
A1: SINTÉTICO — NO ES UNA INVERSIÓN
A2: Concepto | B2: Reportado | C2: Ajuste | D2: Normalizado | E2: Motivo | F2: Fuente
A3: Ingresos último año | B3: 1000 | C3: 0 | D3: =B3+C3 -> 1000 | E3: Sin ajustes; documentar cada ajuste real | F3: synthetic-annual

Sheet Supuestos
A1: SINTÉTICO — NO ES UNA INVERSIÓN
A2: Escenario | B2: Margen EBIT | C2: Impuesto | D2: D&A/ventas | E2: Capex/ventas | F2: CT/ventas | G2: WACC | H2: g terminal | I2: ROIC terminal | J2: Narrativa | K2: Crecimiento año 1 | L2: Crecimiento año 2 | M2: Crecimiento año 3 | N2: Crecimiento año 4 | O2: Crecimiento año 5
A3: adverso | B3: 0.12 | C3: 0.25 | D3: 0.03 | E3: 0.05 | F3: 0.12 | G3: 0.12 | H3: 0.015 | I3: 0.1 | J3: Pérdida de volumen y presión competitiva reducen márgenes; recuperación lenta. | K3: -0.05 | L3: 0 | M3: 0.02 | N3: 0.02 | O3: 0.02
A4: base | B4: 0.18 | C4: 0.25 | D4: 0.03 | E4: 0.05 | F4: 0.12 | G4: 0.1 | H4: 0.02 | I4: 0.15 | J4: Crecimiento de volumen moderado y precios estables; reinversión disciplinada. | K4: 0.06 | L4: 0.05 | M4: 0.04 | N4: 0.03 | O4: 0.03
A5: favorable | B5: 0.22 | C5: 0.25 | D5: 0.03 | E5: 0.05 | F5: 0.12 | G5: 0.09 | H5: 0.025 | I5: 0.18 | J5: Mayor utilización de capacidad y expansión de segmento elevan rentabilidad. | K5: 0.1 | L5: 0.08 | M5: 0.06 | N5: 0.05 | O5: 0.04
A8: Moneda | B8: USD
A9: Base flujos | B9: nominal
A10: Base tasas | B10: nominal
A11: Ingresos iniciales | B11: 1000
A12: Deuda | B12: 200
A13: Caja | B13: 50
A14: Activos no operativos | B14: 10
A15: Minorías | B15: 5
A16: Acciones diluidas | B16: 100
A17: Acciones/instrumento | B17: 1
A18: Pasivos arrendamientos | B18: 0
A19: Tratamiento leases | B19: operating_in_cashflows

Sheet Proyecciones
A1: SINTÉTICO — NO ES UNA INVERSIÓN
A2: Escenario | B2: Año | C2: Ingresos | D2: EBIT | E2: NOPAT | F2: D&A | G2: Capex | H2: Delta CT | I2: FCFF | J2: VP
A3: adverso | B3: 1 | C3: =Supuestos!$B$11*(1+Supuestos!K3) -> 950 | D3: =C3*Supuestos!B3 -> 114 | E3: =D3*(1-Supuestos!C3) -> 85.5 | F3: =C3*Supuestos!D3 -> 28.5 | G3: =C3*Supuestos!E3 -> 47.5 | H3: =(C3-Supuestos!$B$11)*Supuestos!F3 -> -6 | I3: =E3+F3-G3-H3 -> 72.5 | J3: =I3/(1+Supuestos!G3)^B3 -> 64.732143
A4: adverso | B4: 2 | C4: =C3*(1+Supuestos!L3) -> 950 | D4: =C4*Supuestos!B3 -> 114 | E4: =D4*(1-Supuestos!C3) -> 85.5 | F4: =C4*Supuestos!D3 -> 28.5 | G4: =C4*Supuestos!E3 -> 47.5 | H4: =(C4-C3)*Supuestos!F3 -> 0 | I4: =E4+F4-G4-H4 -> 66.5 | J4: =I4/(1+Supuestos!G3)^B4 -> 53.013393
A5: adverso | B5: 3 | C5: =C4*(1+Supuestos!M3) -> 969 | D5: =C5*Supuestos!B3 -> 116.28 | E5: =D5*(1-Supuestos!C3) -> 87.21 | F5: =C5*Supuestos!D3 -> 29.07 | G5: =C5*Supuestos!E3 -> 48.45 | H5: =(C5-C4)*Supuestos!F3 -> 2.28 | I5: =E5+F5-G5-H5 -> 65.55 | J5: =I5/(1+Supuestos!G3)^B5 -> 46.657195
A6: adverso | B6: 4 | C6: =C5*(1+Supuestos!N3) -> 988.38 | D6: =C6*Supuestos!B3 -> 118.6056 | E6: =D6*(1-Supuestos!C3) -> 88.9542 | F6: =C6*Supuestos!D3 -> 29.6514 | G6: =C6*Supuestos!E3 -> 49.419 | H6: =(C6-C5)*Supuestos!F3 -> 2.3256 | I6: =E6+F6-G6-H6 -> 66.861 | J6: =I6/(1+Supuestos!G3)^B6 -> 42.491374
A7: adverso | B7: 5 | C7: =C6*(1+Supuestos!O3) -> 1008.1476 | D7: =C7*Supuestos!B3 -> 120.97771 | E7: =D7*(1-Supuestos!C3) -> 90.733284 | F7: =C7*Supuestos!D3 -> 30.244428 | G7: =C7*Supuestos!E3 -> 50.40738 | H7: =(C7-C6)*Supuestos!F3 -> 2.372112 | I7: =E7+F7-G7-H7 -> 68.19822 | J7: =I7/(1+Supuestos!G3)^B7 -> 38.697502
A8: base | B8: 1 | C8: =Supuestos!$B$11*(1+Supuestos!K4) -> 1060 | D8: =C8*Supuestos!B4 -> 190.8 | E8: =D8*(1-Supuestos!C4) -> 143.1 | F8: =C8*Supuestos!D4 -> 31.8 | G8: =C8*Supuestos!E4 -> 53 | H8: =(C8-Supuestos!$B$11)*Supuestos!F4 -> 7.2 | I8: =E8+F8-G8-H8 -> 114.7 | J8: =I8/(1+Supuestos!G4)^B8 -> 104.27273
A9: base | B9: 2 | C9: =C8*(1+Supuestos!L4) -> 1113 | D9: =C9*Supuestos!B4 -> 200.34 | E9: =D9*(1-Supuestos!C4) -> 150.255 | F9: =C9*Supuestos!D4 -> 33.39 | G9: =C9*Supuestos!E4 -> 55.65 | H9: =(C9-C8)*Supuestos!F4 -> 6.36 | I9: =E9+F9-G9-H9 -> 121.635 | J9: =I9/(1+Supuestos!G4)^B9 -> 100.52479
A10: base | B10: 3 | C10: =C9*(1+Supuestos!M4) -> 1157.52 | D10: =C10*Supuestos!B4 -> 208.3536 | E10: =D10*(1-Supuestos!C4) -> 156.2652 | F10: =C10*Supuestos!D4 -> 34.7256 | G10: =C10*Supuestos!E4 -> 57.876 | H10: =(C10-C9)*Supuestos!F4 -> 5.3424 | I10: =E10+F10-G10-H10 -> 127.7724 | J10: =I10/(1+Supuestos!G4)^B10 -> 95.997295
A11: base | B11: 4 | C11: =C10*(1+Supuestos!N4) -> 1192.2456 | D11: =C11*Supuestos!B4 -> 214.60421 | E11: =D11*(1-Supuestos!C4) -> 160.95316 | F11: =C11*Supuestos!D4 -> 35.767368 | G11: =C11*Supuestos!E4 -> 59.61228 | H11: =(C11-C10)*Supuestos!F4 -> 4.167072 | I11: =E11+F11-G11-H11 -> 132.94117 | J11: =I11/(1+Supuestos!G4)^B11 -> 90.800609
A12: base | B12: 5 | C12: =C11*(1+Supuestos!O4) -> 1228.013 | D12: =C12*Supuestos!B4 -> 221.04233 | E12: =D12*(1-Supuestos!C4) -> 165.78175 | F12: =C12*Supuestos!D4 -> 36.840389 | G12: =C12*Supuestos!E4 -> 61.400648 | H12: =(C12-C11)*Supuestos!F4 -> 4.2920842 | I12: =E12+F12-G12-H12 -> 136.92941 | J12: =I12/(1+Supuestos!G4)^B12 -> 85.022389
A13: favorable | B13: 1 | C13: =Supuestos!$B$11*(1+Supuestos!K5) -> 1100 | D13: =C13*Supuestos!B5 -> 242 | E13: =D13*(1-Supuestos!C5) -> 181.5 | F13: =C13*Supuestos!D5 -> 33 | G13: =C13*Supuestos!E5 -> 55 | H13: =(C13-Supuestos!$B$11)*Supuestos!F5 -> 12 | I13: =E13+F13-G13-H13 -> 147.5 | J13: =I13/(1+Supuestos!G5)^B13 -> 135.3211
A14: favorable | B14: 2 | C14: =C13*(1+Supuestos!L5) -> 1188 | D14: =C14*Supuestos!B5 -> 261.36 | E14: =D14*(1-Supuestos!C5) -> 196.02 | F14: =C14*Supuestos!D5 -> 35.64 | G14: =C14*Supuestos!E5 -> 59.4 | H14: =(C14-C13)*Supuestos!F5 -> 10.56 | I14: =E14+F14-G14-H14 -> 161.7 | J14: =I14/(1+Supuestos!G5)^B14 -> 136.09965
A15: favorable | B15: 3 | C15: =C14*(1+Supuestos!M5) -> 1259.28 | D15: =C15*Supuestos!B5 -> 277.0416 | E15: =D15*(1-Supuestos!C5) -> 207.7812 | F15: =C15*Supuestos!D5 -> 37.7784 | G15: =C15*Supuestos!E5 -> 62.964 | H15: =(C15-C14)*Supuestos!F5 -> 8.5536 | I15: =E15+F15-G15-H15 -> 174.042 | J15: =I15/(1+Supuestos!G5)^B15 -> 134.39236
A16: favorable | B16: 4 | C16: =C15*(1+Supuestos!N5) -> 1322.244 | D16: =C16*Supuestos!B5 -> 290.89368 | E16: =D16*(1-Supuestos!C5) -> 218.17026 | F16: =C16*Supuestos!D5 -> 39.66732 | G16: =C16*Supuestos!E5 -> 66.1122 | H16: =(C16-C15)*Supuestos!F5 -> 7.55568 | I16: =E16+F16-G16-H16 -> 184.1697 | J16: =I16/(1+Supuestos!G5)^B16 -> 130.47046
A17: favorable | B17: 5 | C17: =C16*(1+Supuestos!O5) -> 1375.1338 | D17: =C17*Supuestos!B5 -> 302.52943 | E17: =D17*(1-Supuestos!C5) -> 226.89707 | F17: =C17*Supuestos!D5 -> 41.254013 | G17: =C17*Supuestos!E5 -> 68.756688 | H17: =(C17-C16)*Supuestos!F5 -> 6.3467712 | I17: =E17+F17-G17-H17 -> 193.04762 | J17: =I17/(1+Supuestos!G5)^B17 -> 125.46771

Sheet Valuacion
A1: SINTÉTICO — NO ES UNA INVERSIÓN
A2: Escenario | B2: FCFF terminal | C2: Valor terminal | D2: VP terminal | E2: EV | F2: Equity | G2: Por acción | H2: Por instrumento | I2: Peso terminal
A3: adverso | B3: =Proyecciones!E7*(1+Supuestos!H3)*(1-Supuestos!H3/Supuestos!I3) -> 78.280141 | C3: =B3/(Supuestos!G3-Supuestos!H3) -> 745.52515 | D3: =C3/(1+Supuestos!G3)^Proyecciones!B7 -> 423.03099 | E3: =SUM(Proyecciones!J3:J7)+D3 -> 668.6226 | F3: =E3-Supuestos!$B$12+Supuestos!$B$13+Supuestos!$B$14-Supuestos!$B$15-Supuestos!$B$18 -> 523.6226 | G3: =F3/Supuestos!$B$16 -> 5.236226 | H3: =G3*Supuestos!$B$17 -> 5.236226 | I3: =IF(E3=0,"N/D",D3/E3) -> 0.63269024
A4: base | B4: =Proyecciones!E12*(1+Supuestos!H4)*(1-Supuestos!H4/Supuestos!I4) -> 146.55107 | C4: =B4/(Supuestos!G4-Supuestos!H4) -> 1831.8883 | D4: =C4/(1+Supuestos!G4)^Proyecciones!B12 -> 1137.4585 | E4: =SUM(Proyecciones!J8:J12)+D4 -> 1614.0763 | F4: =E4-Supuestos!$B$12+Supuestos!$B$13+Supuestos!$B$14-Supuestos!$B$15-Supuestos!$B$18 -> 1469.0763 | G4: =F4/Supuestos!$B$16 -> 14.690763 | H4: =G4*Supuestos!$B$17 -> 14.690763 | I4: =IF(E4=0,"N/D",D4/E4) -> 0.70471173
A5: favorable | B5: =Proyecciones!E17*(1+Supuestos!H5)*(1-Supuestos!H5/Supuestos!I5) -> 200.26818 | C5: =B5/(Supuestos!G5-Supuestos!H5) -> 3081.0489 | D5: =C5/(1+Supuestos!G5)^Proyecciones!B17 -> 2002.4704 | E5: =SUM(Proyecciones!J13:J17)+D5 -> 2664.2217 | F5: =E5-Supuestos!$B$12+Supuestos!$B$13+Supuestos!$B$14-Supuestos!$B$15-Supuestos!$B$18 -> 2519.2217 | G5: =F5/Supuestos!$B$16 -> 25.192217 | H5: =G5*Supuestos!$B$17 -> 25.192217 | I5: =IF(E5=0,"N/D",D5/E5) -> 0.75161553

Sheet Sensibilidades
A1: SINTÉTICO — NO ES UNA INVERSIÓN
A2: WACC | B2: g | C2: Por instrumento (base)
A3: 0.09 | B3: 0.015 | C3: =(Proyecciones!I8/(1+A3)^Proyecciones!B8+Proyecciones!I9/(1+A3)^Proyecciones!B9+Proyecciones!I10/(1+A3)^Proyecciones!B10+Proyecciones!I11/(1+A3)^Proyecciones!B11+Proyecciones!I12/(1+A3)^Proyecciones!B12+Proyecciones!E12*(1+B3)*(1-B3/Supuestos!I4)/(A3-B3)/(1+A3)^Proyecciones!B12-Supuestos!$B$12+Supuestos!$B$13+Supuestos!$B$14-Supuestos!$B$15-Supuestos!$B$18)/Supuestos!$B$16*Supuestos!$B$17 -> 16.568
A4: 0.09 | B4: 0.02 | C4: =(Proyecciones!I8/(1+A4)^Proyecciones!B8+Proyecciones!I9/(1+A4)^Proyecciones!B9+Proyecciones!I10/(1+A4)^Proyecciones!B10+Proyecciones!I11/(1+A4)^Proyecciones!B11+Proyecciones!I12/(1+A4)^Proyecciones!B12+Proyecciones!E12*(1+B4)*(1-B4/Supuestos!I4)/(A4-B4)/(1+A4)^Proyecciones!B12-Supuestos!$B$12+Supuestos!$B$13+Supuestos!$B$14-Supuestos!$B$15-Supuestos!$B$18)/Supuestos!$B$16*Supuestos!$B$17 -> 17.051321
A5: 0.09 | B5: 0.025 | C5: =(Proyecciones!I8/(1+A5)^Proyecciones!B8+Proyecciones!I9/(1+A5)^Proyecciones!B9+Proyecciones!I10/(1+A5)^Proyecciones!B10+Proyecciones!I11/(1+A5)^Proyecciones!B11+Proyecciones!I12/(1+A5)^Proyecciones!B12+Proyecciones!E12*(1+B5)*(1-B5/Supuestos!I4)/(A5-B5)/(1+A5)^Proyecciones!B12-Supuestos!$B$12+Supuestos!$B$13+Supuestos!$B$14-Supuestos!$B$15-Supuestos!$B$18)/Supuestos!$B$16*Supuestos!$B$17 -> 17.603474
A6: 0.1 | B6: 0.015 | C6: =(Proyecciones!I8/(1+A6)^Proyecciones!B8+Proyecciones!I9/(1+A6)^Proyecciones!B9+Proyecciones!I10/(1+A6)^Proyecciones!B10+Proyecciones!I11/(1+A6)^Proyecciones!B11+Proyecciones!I12/(1+A6)^Proyecciones!B12+Proyecciones!E12*(1+B6)*(1-B6/Supuestos!I4)/(A6-B6)/(1+A6)^Proyecciones!B12-Supuestos!$B$12+Supuestos!$B$13+Supuestos!$B$14-Supuestos!$B$15-Supuestos!$B$18)/Supuestos!$B$16*Supuestos!$B$17 -> 14.378924
A7: 0.1 | B7: 0.02 | C7: =(Proyecciones!I8/(1+A7)^Proyecciones!B8+Proyecciones!I9/(1+A7)^Proyecciones!B9+Proyecciones!I10/(1+A7)^Proyecciones!B10+Proyecciones!I11/(1+A7)^Proyecciones!B11+Proyecciones!I12/(1+A7)^Proyecciones!B12+Proyecciones!E12*(1+B7)*(1-B7/Supuestos!I4)/(A7-B7)/(1+A7)^Proyecciones!B12-Supuestos!$B$12+Supuestos!$B$13+Supuestos!$B$14-Supuestos!$B$15-Supuestos!$B$18)/Supuestos!$B$16*Supuestos!$B$17 -> 14.690763
A8: 0.1 | B8: 0.025 | C8: =(Proyecciones!I8/(1+A8)^Proyecciones!B8+Proyecciones!I9/(1+A8)^Proyecciones!B9+Proyecciones!I10/(1+A8)^Proyecciones!B10+Proyecciones!I11/(1+A8)^Proyecciones!B11+Proyecciones!I12/(1+A8)^Proyecciones!B12+Proyecciones!E12*(1+B8)*(1-B8/Supuestos!I4)/(A8-B8)/(1+A8)^Proyecciones!B12-Supuestos!$B$12+Supuestos!$B$13+Supuestos!$B$14-Supuestos!$B$15-Supuestos!$B$18)/Supuestos!$B$16*Supuestos!$B$17 -> 15.039607
A9: 0.11 | B9: 0.015 | C9: =(Proyecciones!I8/(1+A9)^Proyecciones!B8+Proyecciones!I9/(1+A9)^Proyecciones!B9+Proyecciones!I10/(1+A9)^Proyecciones!B10+Proyecciones!I11/(1+A9)^Proyecciones!B11+Proyecciones!I12/(1+A9)^Proyecciones!B12+Proyecciones!E12*(1+B9)*(1-B9/Supuestos!I4)/(A9-B9)/(1+A9)^Proyecciones!B12-Supuestos!$B$12+Supuestos!$B$13+Supuestos!$B$14-Supuestos!$B$15-Supuestos!$B$18)/Supuestos!$B$16*Supuestos!$B$17 -> 12.653486
A10: 0.11 | B10: 0.02 | C10: =(Proyecciones!I8/(1+A10)^Proyecciones!B8+Proyecciones!I9/(1+A10)^Proyecciones!B9+Proyecciones!I10/(1+A10)^Proyecciones!B10+Proyecciones!I11/(1+A10)^Proyecciones!B11+Proyecciones!I12/(1+A10)^Proyecciones!B12+Proyecciones!E12*(1+B10)*(1-B10/Supuestos!I4)/(A10-B10)/(1+A10)^Proyecciones!B12-Supuestos!$B$12+Supuestos!$B$13+Supuestos!$B$14-Supuestos!$B$15-Supuestos!$B$18)/Supuestos!$B$16*Supuestos!$B$17 -> 12.856581
A11: 0.11 | B11: 0.025 | C11: =(Proyecciones!I8/(1+A11)^Proyecciones!B8+Proyecciones!I9/(1+A11)^Proyecciones!B9+Proyecciones!I10/(1+A11)^Proyecciones!B10+Proyecciones!I11/(1+A11)^Proyecciones!B11+Proyecciones!I12/(1+A11)^Proyecciones!B12+Proyecciones!E12*(1+B11)*(1-B11/Supuestos!I4)/(A11-B11)/(1+A11)^Proyecciones!B12-Supuestos!$B$12+Supuestos!$B$13+Supuestos!$B$14-Supuestos!$B$15-Supuestos!$B$18)/Supuestos!$B$16*Supuestos!$B$17 -> 13.079712

Sheet Controles
A1: SINTÉTICO — NO ES UNA INVERSIÓN
A2: Control | B2: Resultado | C2: Criterio
A3: Balance 2020 | B3: =IF(COUNT(Historicos!G3:I3)=3,Historicos!G3-Historicos!H3-Historicos!I3,"N/D") -> 0 | C3: Debe ser cero; N/D bloquea conciliación
A4: Balance 2021 | B4: =IF(COUNT(Historicos!G4:I4)=3,Historicos!G4-Historicos!H4-Historicos!I4,"N/D") -> 0 | C4: Debe ser cero; N/D bloquea conciliación
A5: Balance 2022 | B5: =IF(COUNT(Historicos!G5:I5)=3,Historicos!G5-Historicos!H5-Historicos!I5,"N/D") -> 0 | C5: Debe ser cero; N/D bloquea conciliación
A6: Balance 2023 | B6: =IF(COUNT(Historicos!G6:I6)=3,Historicos!G6-Historicos!H6-Historicos!I6,"N/D") -> 0 | C6: Debe ser cero; N/D bloquea conciliación
A7: Balance 2024 | B7: =IF(COUNT(Historicos!G7:I7)=3,Historicos!G7-Historicos!H7-Historicos!I7,"N/D") -> 0 | C7: Debe ser cero; N/D bloquea conciliación
A10: Base flujos = tasas | B10: =Supuestos!B9=Supuestos!B10 -> TRUE
A12: Revisión independiente | B12: PENDIENTE: evidencia y revisor distinto del autor
A14: Cachés iniciales | B14: Calculados en Python; recalcular fórmulas tras editar en Excel/LibreOffice
